{"add": {"doc": {"field": [{"@name": "docid", "#text": "BR-BT.04350"}, {"@name": "filename", "#text": "BTP_1984_27_3_10_Inovacao_tecnologica.pdf"}, {"@name": "filetype", "#text": "PDF"}, {"@name": "text", "#text": "UMA INOVA\u00c7\u00c3O TECNOL\u00d3GICA NUM CENTRO DE P &amp; D DE PAI'S EM DESENVOLVIMENTO*\nSERGIO TORRES DA COSTA, Divis\u00e3o de Tecnologia de Processos, Centro de Pesquisas e DORODAME MOURA WX\u00c3O, Assist\u00eancia de Planejamento, Centro de Pesquisas (\u00e0 \u00e9poca de elabora\u00e7\u00e3o do trabalho, o autor achava-se lotado na Divis\u00e3o de Tecnologia de Processos).\nRESUMO \u2014 Descreve-se o desenvolvimento de uma tecnologia apropriada ao Brasil \u2014 produ\u00e7\u00e3o de eteno a partir do etanol \u2014 com destaque do entrosamento que deve haver entre as atividades de pesquisa e de engenharia b\u00e1sica e do estudo dos fundamentos, principalmente os ligados \u00e0 catalise a \u00e0 cin\u00e9tica qu\u00edmica, em escalas de laborat\u00f3rio e unidade-piloto.\nA tecnologia desenvolvida \u2014 baseada num reator adiab\u00e1tico \u2014 \u00e9 um indiscut\u00edvel sucesso industrial e comercial\nABSTRACT - The development of a technology appropriate to Brazil - production of ethene from ethanol - is described, with emphasis on the association of research with basic engineering, Und on the research of fundamentals, especially those related to catalysis and chemical kinetics, on laboratory and pilot-plant scales.\nThe technology developed, based on an adiabatic reactor, is an undeniable industrial and commercial success.\n(Originais recebidos em l-H-84.)\n1\t- INTRODU\u00c7\u00c3O\nO processo de industrializa\u00e7\u00e3o dos pa\u00edses menos desenvolvidos se realizou \u00e0s custas de uma importa\u00e7\u00e3o maci\u00e7a da tecnologia existente nos pa\u00edses j\u00e1 industrializados, em um mecanismo que se convencionou chamar industrializa\u00e7\u00e3o por substitui\u00e7\u00e3o de importa\u00e7\u00f5es.\nPor esse motivo, a atividade de pesquisa e desenvolvimento nesses pa\u00edses est\u00e1, normalmente, restrita \u00e0 adapta\u00e7\u00e3o dessa tecnologia importada para as condi\u00e7\u00f5es de mercado e mat\u00e9ria-prima existentes nesses pa\u00edses.\nApesar disto, h\u00e1 ainda campo para a inova\u00e7\u00e3o tecnol\u00f3gica em situa\u00e7\u00f5es especiais, ligadas principalmente ao aproveitamento de recursos naturais. O presente trabalho descreve um desses casos, com o desenvolvimento de tecnologia apropriada ao Brasil, e envolvendo uma real inova\u00e7\u00e3o tecnol\u00f3gica.\nO exemplo descrito, referente \u00e0 tecnologia de obten\u00e7\u00e3o de eteno a partir de etanol, ilustra bem um exemplo surgido em decorr\u00eancia da demanda de mercado (market pull}, pois j\u00e1 existiam condi\u00e7\u00f5es conjunturais que mostravam a necessidade de uma tecnologia nova ou adaptada.\nSua import\u00e2ncia \u00e9 maior por tratar-se de uma tecnologia apropriada, devido \u00e0s caracter\u00edsticas tanto do processo quanto da regi\u00e3o onde foi implantada.\nO trabalho nana desde a id\u00e9ia inicial, que motivou as primeiras especula\u00e7\u00f5es sobre o assunto, passando por sua evolu\u00e7\u00e3o e pela busca de solu\u00e7\u00f5es, at\u00e9 a forma final com seus resultados.\nProcura-se destacar o entrosamento que deve haver entre as atividades de pesquisa e de engenharia b\u00e1sica, indispens\u00e1vel para a realiza\u00e7\u00e3o do processo, por envolver, por parte da pesquisa, a cria\u00e7\u00e3o dp conhecimento e \u00f3 levantamento das informa\u00e7\u00f5es tecnol\u00f3gicas, e, por parte da engenharia b\u00e1sica, a arruma\u00e7\u00e3o desses conhecimentos de forma ordenada.\n\u00canfase especial \u00e9 dada ao trabalho desenvolvido pela pesquisa tecnol\u00f3gica, realizada a n\u00edvel de escala de bancada de laborat\u00f3rio \u2014 com o estudo dos fundamentos, principalmente os ligados \u00e0 cat\u00e1lise e \u00e0 cin\u00e9tica qu\u00edmica \u2014 e de escala-piloto, onde a preocupa\u00e7\u00e3o primordial se prende aos aspectos tecnol\u00f3gicos do processo como um todo.\nJulgou-se necess\u00e1rio tal destaque, dada a pouca compreens\u00e3o ainda existente em pa\u00edses no est\u00e1gio de desenvolvimento do Brasil para com o papel da pesquisadecnol\u00f3gi-ca dentro de um processo de inova\u00e7\u00e3o.\nConsiderou-se o caso escolhido como ideal para tal aprecia\u00e7\u00e3o, pois, al\u00e9m de envolver em seu desenvolvimento todos os est\u00e1gios cl\u00e1ssicos da inova\u00e7\u00e3o tecnol\u00f3gica, desde a pesquisa em bancada at\u00e9 a opera\u00e7\u00e3o da unidade industrial, trata-se, tamb\u00e9m, de uma tecnologia de indiscut\u00edvel sucesso industrial e comercial, j\u00e1 que est\u00e1 em estudos a possibilidade de amplia\u00e7\u00e3o da unidade industrial, havendo1 interesse de outros pa\u00edses na utiliza\u00e7\u00e3o do processo e na presta\u00e7\u00e3o de assist\u00eancia t\u00e9cnica.\n2\t- HIST\u00d3RICO\nO projeto em quest\u00e3o foi desenvolvido pela PETRO-BR\u00c2S, atrav\u00e9s do seu Centro de Pesquisas e Desenvolvimento Leopoldo A. Miguez de Mello (CENPES), envolvendo a \u00e1rea de pesquisa e engenharia b\u00e1sica, num esfor\u00e7o integrado para a resolu\u00e7\u00e3o de um problema tecnol\u00f3gico t\u00edpico do caso brasileiro.\nA Salgema Ind\u00fastrias Qu\u00edmicas S.A. se havia proposto, a partir dos dep\u00f3sitos de salgema da regi\u00e3o de Macei\u00f3, a produzir soda c\u00e1ustica para o mercado interno em geral, e cloro, destinado ao P\u00f3lo Petroqu\u00edmico de Cama\u00e7ari, para a produ\u00e7\u00e3o de P.V.C. (policloreto de vinila).\nA inviabilidade do transporte do cloro por superf\u00edcie e por via mar\u00edtima fez com que se decidisse descart\u00e1-lo ou transport\u00e1-lo indiretamente, transformando-o em \u00e1cido clor\u00eddrico, pela utiliza\u00e7\u00e3o de uma corrente de hidrog\u00eanio\n* Baseado no trabalho intermodular apresentado por Sergio Torres da Costa no Programa de Treinamento em Administra\u00e7\u00e3o da Pesquisa Cient\u00edfica e Tecnol\u00f3gica - IX Ciclo \u2014 do Instituto de Administra\u00e7\u00e3o da Faculdade de Economia e Administra\u00e7\u00e3o da Universidade de S\u00e3o Paulo.\ndispon\u00edvel. Posteriormente, esse transporte passou a ser feito, ainda indiretamente, transformando-se o cloro em dicloroetano, atrav\u00e9s de sua rea\u00e7\u00e3o com o eteno produzido no pr\u00f3prio P\u00f3lo Petroqu\u00edmico de Cama\u00e7ari, liberando, desta forma, a corrente de hidrog\u00eanio que era consumida, para ser queimada nas caldeiras.\nNaturalmente que o desej\u00e1vel para o caso seria a produ\u00e7\u00e3o de eteno na pr\u00f3pria ind\u00fastria. Assim \u00e9 que a Salgema solicitou ao CENPES uma avalia\u00e7\u00e3o do processo de obten\u00e7\u00e3o de eteno a partir de etanol, uma vez que havia disponibilidade dessa mat\u00e9ria-prima na regi\u00e3o de Macei\u00f3.\n\u00c9 preciso lembrar que j\u00e1 existiram no Brasil outras unidades produtoras de eteno via etanol: uma da Union Carbide, em Cubat\u00e3o-SP, de 12 000 t/ano de eteno, que havia sido desativada por ser antiecon\u00f4mica, e outra da Eletrocloro, em Ribeir\u00e3o Pires-SP, com capacidade de 10 000 t/ano.\nA partir de contatos com as companhias ent\u00e3o produtoras e do estabelecimento de um contrato de coopera\u00e7\u00e3o t\u00e9cnica com a Eletrocloro, que permitiu o fornecimento de dados operacionais de sua unidade, o CENPES sentiu que poder\u00eda desenvolver o projeto b\u00e1sico no pr\u00f3prio Pa\u00eds.\nA conjuntura era favor\u00e1vel, uma vez que as grandes unidades produtoras de eteno o produzem a partir de pir\u00f3lise de nafta, produto derivado do petr\u00f3leo, em grande parte importado. A alternativa do \u00e1lcool como mat\u00e9ria-prima apresentava, pois, grande atrativo, especialmente em se tratando de Pa\u00eds n\u00e3o auto-suficiente em petr\u00f3leo, mas com possibilidade de produ\u00e7\u00e3o de produtos agr\u00edcolas pass\u00edveis de serem transformados em \u00e1lcool, reduzindo assim o consumo de derivados de petr\u00f3leo e, conseq\u00fcent\u00e9ment\u00ea, o d\u00e9ficit no balan\u00e7o de pagamentos.\nAssim \u00e9 que originariamente se idealizou executar um projeto de engenharia b\u00e1sica de uma unidade industrial de 60 000 t/ano de eteno, utilizando-se o processo isot\u00e9rmico com reatores multitubulares, conhecido at\u00e9 ent\u00e3o. Seria, portanto, um scale up da unidade em opera\u00e7\u00e3o da Eletrocloro, ainda que incorporando certas melhorias.\n\u00c9 preciso deixar claro que mesmo um projeto de aumento de escala como este, que \u00e0 primeira vista pode parecer simples de ser desenvolvido, j\u00e1 que m\u00e9todos operacionais da unidade menor s\u00e3o dominados de forma ampla, necessita substancialmente de conhecimentos gerados pela pesquisa, tanto a n\u00edvel de unidades de bancada, como a n\u00edvel de unidades-piloto. Sem a gera\u00e7\u00e3o desses dados, o m\u00e1ximo que se conseguir\u00eda fazer seria um projeto para a unidade de mesmo porte da existente: uma mera c\u00f3pia, ainda que com a incorpora\u00e7\u00e3o de algumas melhorias. Tendo consci\u00eancia dessa realidade, o CENPES iniciou uma s\u00e9rie de investiga\u00e7\u00f5es, na \u00e1rea de pesquisa, que viessem atender \u00e0 necessidade da engenharia b\u00e1sica, tanto em rela\u00e7\u00e3o \u00e0s vari\u00e1veis operacionais do processo isot\u00e9rmico, quanto em rela\u00e7\u00e3o \u00e0 escolha do catalisador a ser utilizado.\n3\t- AVALIA\u00c7\u00c3O DO DESEMPENHO DE CATALISADORES EM UNIDADE DE BANCADA - A ESCOLHA DO CATALISADOR\n\u00c9 interessante notar que, apesar de a desidrata\u00e7\u00e3o de etanol haver sido estudada durante longos \u00e1nos, a dificuldade na interpreta\u00e7\u00e3o dos dados dispon\u00edveis era um fato, pois n\u00e3o se tinha uma caracteriza\u00e7\u00e3o suficiente dos catalisadores empregados, bem como existiam discrep\u00e2ncias\nmuito grandes no que diz respeito aos produtos secund\u00e1rios gerados no processo.\nEm parte, isto se devia aos m\u00e9todos de an\u00e1lise existentes no passado, pois m\u00e9todos anal\u00edticos precisos, como a cromatografia, s\u00f3 se tomaram difundidos quando a desidrata\u00e7\u00e3o de \u00e1lcool j\u00e1 perdera import\u00e2ncia econ\u00f4mica.\nConhecendo-se, a partir da literatura existente, os mecanismos das rea\u00e7\u00f5es envolvidas no processo e as caracter\u00edsticas f\u00edsico-qu\u00edmicas dos catalisadores us\u00e1veis no processo de desidrata\u00e7\u00e3o do etanol, p\u00f4de-se fazer uma sele\u00e7\u00e3o pr\u00e9via dos mesmos, chegando-se a tr\u00eas diferentes classes: as aluminas, as s\u00edlica-aluminas e os ze\u00f3litos.\nDecidiu-se, ent\u00e3o, escolher o catalisador mais indicado para a rea\u00e7\u00e3o em quest\u00e3o. Assim, fez-se o levantamento experimental de dados de atividade, de seletividade e de vida de cada um dos catalisadores previamente selecionados, sendo tamb\u00e9m importante a determina\u00e7\u00e3o da depend\u00eancia que existe entre essas propriedades e as condi\u00e7\u00f5es de pr\u00e9-tratamento por que passou o catalisador.\nAs experi\u00eancias foram iniciadas utilizando-se etanol puro, isto \u00e9, n\u00e3o-comercial, e. os catalisadores escolhidos dentre os dispon\u00edveis foram:\n\u2014\tda classe das aluminas', um importado, indicado pelo fabricante como apropriado para a rea\u00e7\u00e3o, e outro desenvolvido no pr\u00f3prio CENPES;\n\u2014\tda classe das s\u00edlica-aluminas: o pr\u00f3prio catalisador utilizado no processo isot\u00e9rmico da Eletrocloro e um outro usado em craqueamento catal\u00edtico, ambos de proced\u00eancia estrangeira, al\u00e9m de uma argila nacional;\n\u2014\tda classe dos ze\u00f3litos: uma mordenita e um catalisador zeol\u00edtico usado em craqueamento catal\u00edtico, ambos, portanto, estrangeiros.\nA unidade de bancada era formada por um microrrea-tor acoplado a um sistema de an\u00e1lise cromatogr\u00e1fica. A capacidade do microrreator usado, em leito fixo, era da ordem de 0,5 a 2 gramas de catalisador, em forma de p\u00f3, e o \u00e1lcool era admitido no seu interior numa vaz\u00e3o da ordem de 0,2 a 10 cm3/h.\nOs resultados mostraram que todos os catalisadores desidratavam o etanol, formando eteno, por\u00e9m com diversos graus de convers\u00e3o e seletividade.\nEstudou-se, assim, como a decomposi\u00e7\u00e3o do etanol, a forma\u00e7\u00e3o de eteno e a de subprodutos respondiam a varia\u00e7\u00f5es de temperatura e de velocidade espacial para cada um dos catalisadores.\nOs resultados apontaram as aluminas como sendo os catalisadores mais indicados para o processo em leito fixo, enquanto a mordenita mostrava bom potencial se utilizada em leito fluidizado. Dentre as aluminas, a desenvolvida no pr\u00f3prio CENPES foi a que apresentou melhores resultados.\n4\t- ESTUDOS EM ESCALA-PILOTO: REATOR EM LEITO FIXO ISOT\u00c9RMICO E EM LEITO FLUIDIZADO\nParalelamente \u00e0 escolha do catalisador, feita em unidade de bancada, iniciar\u00e1m-se os estudos em unidade-piloto, para se produzirem as condi\u00e7\u00f5es operacionais da unidade industrial da Eletrocloro, com reatores isot\u00e9rmicos. Utilizou-se a unidade de Reforma\u00e7\u00e3o Catal\u00edtica j\u00e1 existente no\nCENPES, que foi adaptada, e onde o reator existente simularia uma se\u00e7\u00e3o de um dos tubos que havia no reator, industrial.\nUsou-se como carga um \u00e1lcool industrial ou um \u00e1lcool retificado. A vaz\u00e3o utilizada na unidade-piloto era da ordem de 400 cm3/h, com uma carga de catalisador igual a 300 g no reator. A produ\u00e7\u00e3o de eteno nesta unidade se situou em 600 kg/ano.\nTamb\u00e9m foram feitos estudos em unidade-piloto com leito fluidizado, ficando evidenciado que os problemas surgidos elevariam os custos de produ\u00e7\u00e3o e o investimento inicial. Por outro lado, essa rota envolver\u00eda complexidade de opera\u00e7\u00e3o e sofistica\u00e7\u00e3o tecnol\u00f3gica muito maiores.\nDurante a coleta de dados das experi\u00eancias em escala-pi-loto, o grupo da engenharia b\u00e1sica verificou, num estudo preliminar, que o investimento e o custo de opera\u00e7\u00e3o da unidade isot\u00e9rmica a ser projetada seriam elevados, dado o grande porte de seus reatores; verificou tamb\u00e9m que advir\u00edam problemas operacionais no sistema de aquecimento dos mesmos.\nEm raz\u00e3o disto, fizeram-se testes na unidade-piloto com maiores velocidades espaciais, que permitir\u00edam uma redm \u00e7\u00e3o do tamanho dos reatores. Prosseguiu-se, ent\u00e3o, estudando a influ\u00eancia da velocidade espacial no tempo de campanha; a influ\u00eancia da temperatura na rela\u00e7\u00e3o \u00e9ter/ete-no; a deposi\u00e7\u00e3o de coque sobre o catalisador; a forma\u00e7\u00e3o de subprodutos indesej\u00e1veis; e o perfil longitudinal de temperatura no reator.\nO catalisador inicialmente testado foi o de s\u00edlica-alu-mina utilizado pela Eletrocloro. Posteriormente, com os resultados da unidade de bancada, testaram-se tamb\u00e9m os dados obtidos em escala de bancada: dentre as aluminas, aquela a apresentar melhor desempenho foi uma desenvolvida no pr\u00f3prio CENPES.\nOs dados oriundos da unidade-piloto vieram confirmar que se estava diante de uma solu\u00e7\u00e3o economicamente invi\u00e1vel, pois persistiam as grandes dimens\u00f5es de reatores e os custos exagerados.\n5\t- A NOVA CONCEP\u00c7\u00c3O: REATOR ADIAB\u00c1TICO - DESENVOLVIMENTO EM UNIDADE-PILOTO E DE BANCADA\nDiante da impossibilidade h\u00e1 pouco citada, em lugar da frustra\u00e7\u00e3o, surgiu a inova\u00e7\u00e3o tecnol\u00f3gica: pensou-se num novo conceito de sistema reacional. Em lugar de reatores multitubulares aquecidos em fornalhas ou atrav\u00e9s de fluido circulante, ter-se-iam reatores adiab\u00e1ticos, onde o calor seria fornecido \u00e0 carga antes de sua entrada no reator, assegurando, \u00e0 sa\u00edda do mesmo, temperatura suficiente para evitar a forma\u00e7\u00e3o de subprodutos indesej\u00e1veis (\u00e9ter et\u00edlico principalmente).\nN\u00e3o se teria conseguido isto apenas aquecendo-se o \u00e1lcool, pois o calor a ser fornecido o decomporia, formando produtos indesej\u00e1veis e ainda prejudicando o catalisador.\nEstudou-se esse problema misturando-se o \u00e1lcool com diluentes, que, uma vez aquecidos, forneciam o calor para a rea\u00e7\u00e3o de desidrata\u00e7\u00e3o do etanol. Foram testados: vapor d\u2019\u00e1gua, nitrog\u00eanio e o pr\u00f3prio eteno.\nA caracter\u00edstica do reator adiab\u00e1tico \u00e9 n\u00e3o apresentar trocas de calor com o meio ambiente, o que em unidades de grande porte \u00e9 facilmente conseguido, j\u00e1 que a quantidade de calor trocada pode ser considerada desprez\u00edvel,\nface \u00e0s quantidades totais envolvidas e uma vez que nestes reatores a rela\u00e7\u00e3o \u00e1rea externa/volume \u00e9 pequena. Em unidade de pequeno porte, por\u00e9m, como a unidade-piloto utilizada nos estudos, a perda de calor para o exterior tem que ser compensada fornecendo-se calor externo \u00e0s paredes do reator.\nO que se fez nos estudos realizados na unidade-piloto de Reforma\u00e7\u00e3o Catal\u00edtica, que at\u00e9 ent\u00e3o vinha sendo utilizada no processo isot\u00e9rmico, foi uma simula\u00e7\u00e3o do processo adiab\u00e1tico. Num esquema, havia um reator gerando efluente, que seria o reciclo simulado do reator adiab\u00e1tico. Num outro esquema, o reciclo foi simulado por uma corrente de vapor d\u2019\u00e1gua e eteno comercial; e, em um terceiro procedimento, o reciclo era feito apenas com vapor d\u2019\u00e1gua.\nEstudou-se, ent\u00e3o, a influ\u00eancia da raz\u00e3o de reciclo sobre o perfil longitudinal de temperatura do leito de catalisador e o efeito da press\u00e3o sobre o catalisador. Fizeram-se testes de desempenho de aluminas comerciais e de aluminas desenvolvidas no CENPES. Testou-se ainda a configura\u00e7\u00e3o de reatores em cascata, visando \u00e0 diminui\u00e7\u00e3o do investimento e do custo operacional do processo.\nConv\u00e9m salientar que, no momento da partida para o processo adiab\u00e1tico, houve solicita\u00e7\u00e3o de dados n\u00e3o s\u00f3 da unitade-piloto, mas tamb\u00e9m de estudos da unidade de bancada. Levantaram-se nessas unidades dados sobre a influ\u00eancia da press\u00e3o e do tempo de contato do \u00e1lcool com o catalisador sobre o rendimento da rea\u00e7\u00e3o. Teve-se em mira: o estudo do efeito da dilui\u00e7\u00e3o da carga com g\u00e1s inerte e com vapor d\u2019\u00e1gua e o efeito das press\u00f5es, velocidades espaciais e rela\u00e7\u00f5es diluente/carga sobre a rea\u00e7\u00e3o e o catalisador.\nProblemas n\u00e3o suficientemente explicados nas corridas da unidade-piloto eram estudados na unidade de bancada, numa forma mais sistem\u00e1tica, uma vez que essas unidades se prestam a dar respostas em espa\u00e7o de tempo mais curto que o da unidade-piloto; tais resultados serviam de orienta\u00e7\u00e3o para novas corridas nesta \u00faltima. O efeito de reciclo sobre a efici\u00eancia da rea\u00e7\u00e3o \u00e9 um exemplo que pode ser citado dentre aqueles que necessitaram de um estudo mais sistem\u00e1tico em unidade de bancada, uma vez que havia d\u00favidas quanto ao resultado ruim obtido em determinada corrida na unidade-piloto, se teria sido ou n\u00e3o motivado pelo fato de estar o catalisador desativado.\nEstudos feitos em unidade de bancada serviram, ainda, para fornecer subs\u00eddios \u00e0 engenharia b\u00e1sica sobre como diferentes ligas met\u00e1licas usadas na constru\u00e7\u00e3o de reatores e tubos de fornalha poder\u00edam atuar na decomposi\u00e7\u00e3o do etanol, de forma a ocasionar problemas como a decomposi\u00e7\u00e3o da carga ou a forma\u00e7\u00e3o de produtos indesej\u00e1veis, incluindo-se tamb\u00e9m a deposi\u00e7\u00e3o de coque sobre os diversos materiais estudados.\nTendo em vista a primeira sele\u00e7\u00e3o da classe de catalisadores feita em unidade de bancada e a confirma\u00e7\u00e3o, em unidade-piloto, de que as aluminas eram os catalisadores mais indicados, fez-se uma nova avalia\u00e7\u00e3o, em unidade de bancada, de uma s\u00e9rie de aluminas comerciais e de aluminas desenvolvidas no CENPES. Visava-se com isto estudar a influ\u00eancia de impurezas dessas aluminas, preparadas a partir de mat\u00e9rias-primas diversas sobre a rea\u00e7\u00e3o.\nFez parte, ainda, dos dados fornecidos \u00e0 engenharia b\u00e1sica um estudo termodin\u00e2mico do sistema etanol-\u00e9ter et\u00edlico-\u00e1gua, para que se conhecessem as limita\u00e7\u00f5es termodin\u00e2micas da rea\u00e7\u00e3o no que diz respeito \u00e0 temperatura, press\u00e3o e composi\u00e7\u00e3o iniciais, e com o fim de se obterem\nas necessidades t\u00e9rmicas do sistema adiab\u00e1tico, admitindo-se o equil\u00edbrio do sistema em certas condi\u00e7\u00f5es de temperatura, press\u00e3o e composi\u00e7\u00e3o.\nCom vistas \u00e0 coloca\u00e7\u00e3o do eteno produzido dentro dos limites de pureza desejados, procedeu-se a estudos de alternativas para a sua purifica\u00e7\u00e3o.\nAlgumas das impurezas que contaminam o eteno proveniente da desidrata\u00e7\u00e3o do etanol s\u00e3o removidas facilmente por lavagem e condensa\u00e7\u00e3o, mas as olefinas de tr\u00eas e quatro \u00e1tomos de carbono t\u00eam que ser removidas utilizando-se outros m\u00e9todos. A adsor\u00e7\u00e3o de impurezas sobre um material adsorvente \u00e9 uma sa\u00edda, mas, mesmo assim, h\u00e1 dificuldades t\u00e9cnicas, pois o propeno, em especial, tem adsortividade bem pr\u00f3xima da do eteno.\t\u2022\nPor isso, estudaram-se a termodin\u00e2mica e a cin\u00e9tica do sistema eteno-propeno-carv\u00e3o ativo, para uma determinada faixa de press\u00f5es e temperaturas em uma unidade de bancada, concluindo-se que a separa\u00e7\u00e3o do propeno e produtos mais pesados existentes na corrente de eteno \u00e9 poss\u00edvel, apesar de tamb\u00e9m haver razo\u00e1vel adsor\u00e7\u00e3o desse produto no carv\u00e3o ativo.\nOs resultados provenientes de todos esses estudos, desenvolvidos ao longo de mais de dois anos pela equipe da pesquisa, indicaram ser amplamente vi\u00e1vel e eficaz o processo idealizado com reatores adiab\u00e1ticos.\nSabia-se, ent\u00e3o, que, ao se introduzir como carga no reator a mistura de \u00e1lcool com vapor d\u2019\u00e1gua, ocorrer\u00eda um sens\u00edvel acr\u00e9scimo de rendimento, em conseq\u00fc\u00eancia da diminui\u00e7\u00e3o da forma\u00e7\u00e3o de subprodutos, al\u00e9m de haver uma redu\u00e7\u00e3o dr\u00e1stica na forma\u00e7\u00e3o de coque, e de o catalisador ter sua atividade mantida por um tempo muito mais prolongado.\nNestas condi\u00e7\u00f5es, existia ainda a possibilidade de se operar com press\u00f5es mais elevadas no reator, sem causar perda de convers\u00e3o.\nSabia-se tamb\u00e9m que seria desnecess\u00e1rio realizar qualquer pr\u00e9-tratamento no \u00e1lcool industrial. Al\u00e9m disso, j\u00e1 estava definido o catalisador dispon\u00edvel a ser empregado: uma alumina comercial.\n6\t- ESCALA PROT\u00d3TIPO\nCom tais perspectivas favor\u00e1veis, projetou-se no CEN-PES uma unidade prot\u00f3tipo, constru\u00edda posteriormente junto \u00e0 Refinaria Duque de Caxias, com capacidade de produ\u00e7\u00e3o de 60 t/ano de eteno, para se obter uma confirma\u00e7\u00e3o definitiva do processo. Nessa unidade, a adiabatici-dade do reator foi conseguida por isolamento t\u00e9rmico.\nCom a opera\u00e7\u00e3o da unidade prot\u00f3tipo, foram confirmados os dados obtidos anteriormente e conseguidas as informa\u00e7\u00f5es complementares para a etapa seguinte do projeto da unidade industrial.\nVale salientar que, durante a opera\u00e7\u00e3o da unidade prot\u00f3tipo, as unidades de bancada continuaram a alimentar o desenvolvimento do processo com dados esclarecedores, caracterizando o catalisador e fornecendo explica\u00e7\u00f5es sobre cada uma das ocorr\u00eancias que o prejudicaram.\nCom os par\u00e2metros b\u00e1sicos do processo confirmados em escala prot\u00f3tipo, o CENPES apresentou uma proposta de fornecimento'de engenharia b\u00e1sica \u00e0 Salgema, ao mesmo tempo em que o processo inovador foi patenteado no Brasil e em v\u00e1rios outros pa\u00edses.\nA proposta foi confrontada pela Salgema, quanto aos aspectos t\u00e9cnico e econ\u00f4mico, com outras tecnologias de\nconcorrentes internacionais; a op\u00e7\u00e3o final foi pelo processo nacional, reconhecidamente superior do ponto de vista tecnol\u00f3gico.\n7\t- UNIDADE INDUSTRIAL\nO projeto b\u00e1sico da unidade foi inteiramente elaborado no CENPES, tendo as firmas nacionais empreendido o detalhamento, a fabrica\u00e7\u00e3o de equipamentos, a constru\u00e7\u00e3o civil e a montagem da unidade industrial. Em fins de 1981, entrou em opera\u00e7\u00e3o a unidade de 60 000 t/ano de eteno via etanol, de maior capacidade mundial.\nA partida da opera\u00e7\u00e3o, efetuada pela pr\u00f3pria Salgema, teve a assist\u00eancia t\u00e9cnica do grupo de engenharia b\u00e1sica do CENPES.\nA unidade tem operado satisfatoriamente, confirmando as expectativas, sendo que somente ap\u00f3s vinte meses de opera\u00e7\u00e3o \u00e9 que se programou a primeira regenera\u00e7\u00e3o a ser feita no catalisador, ao passo que no processo isot\u00e9rmico essa regenera\u00e7\u00e3o ocorria a cada trinta dias.\t.\nAos poucos, os resultados retornam ao CENPES, fornecidos pela unidade industrial em opera\u00e7\u00e3o, realimentah-do a capacita\u00e7\u00e3o do grupo e fechando o ciclo de desenvolvimento tecnol\u00f3gico do processo.\nDevido \u00e0 rentabilidade conseguida pela Salgema, esta j\u00e1 solicitou uma amplia\u00e7\u00e3o da capacidade instalada da unidade para 100 000 t/ano de eteno.\nO coroamento de todo esse esfor\u00e7o pode ser traduzido pelo fato de diversos pa\u00edses estarem solicitando ao CENPES a venda dessa tecnologia e assist\u00eancia t\u00e9cnica, uma vez que esse processo pode ser bem aproveitado por pa\u00edses que, possuindo baixa disponibilidade de produtos petroqu\u00edmicos e reduzida produ\u00e7\u00e3o de petr\u00f3leo, podem utilizar a biomassa como fonte de mat\u00e9rias-primas.\nUm primeiro contrato de licenciamento j\u00e1 foi firmado com uma empresa da \u00edndia.\nPode-se ainda citar como uma grande perspectiva futura para complementar o pacote tecnol\u00f3gico a utiliza\u00e7\u00e3o de catalisador nacional, uma vez que a pesquisa indicou que uma alumina desenvolvida no pr\u00f3prio CENPES tinha o melhor desempenho dentre os catalisadores estudados.\nEssa alumina foi produzida em escala de bancada e em escala-piloto, mas seu desenvolvimento tem que ser completado por uma produ\u00e7\u00e3o em escala prot\u00f3tipo e industrial.\nO fato de se ter desenvolvido uma tecnologia inovadora permite exemplificar bem a metodologia de elabora\u00e7\u00e3o de um processo em etapas subsequentes, mostrando a intera\u00e7\u00e3o que deve existir entre os t\u00e9cnicos das diversas \u00e1reas envolvidas. Fica evidenciada a import\u00e2ncia da proximidade de grupos de pesquisa e de engenharia b\u00e1sica; o primeiro \u00e9 respons\u00e1vel pela gera\u00e7\u00e3o e coleta de conhecimentos, os quais ser\u00e3o usados e viabilizados pelo segundo grupo, que os transformar\u00e1 em um pacote que permitir\u00e1 a constru\u00e7\u00e3o e a opera\u00e7\u00e3o da unidade industrial.\nPode-se resumir o desenvolvimento do exemplo descrito com as seguintes etapas:\na)\tidentifica\u00e7\u00e3o das oportunidades apresentadas pelo mercado;\nb)\tpesquisa em unidade de bancada por pessoal especializado em estudos fundamentais;\nc)\tpesquisa em unidade-piloto com pessoal tamb\u00e9m especializado nesses equipamentos;\nd)\tprojeto de uma unidade prot\u00f3tipo para permitir a escalada do processo, com verifica\u00e7\u00e3o dos resultados da pesquisa em escala maior pela engenharia b\u00e1sica;\ne)\tprojeto de engenharia b\u00e1sica para a unidade industrial;\nf)\tprojetos de detalhamento, constru\u00e7\u00e3o civil, fabrica\u00e7\u00e3o de equipamentos e montagem da unidade industrial;\ng)\topera\u00e7\u00e3o da unidade industrial;\nh)\tfornecimento de dados de volta ao grupo de engenharia b\u00e1sica, com a plena consolida\u00e7\u00e3o do dom\u00ednio da tecnologia desenvolvida.\n8\t- CONCLUS\u00d5ES\nO desenvolvimento da tecnologia em quest\u00e3o pode ser considerado um \u00eaxito e serve como um bom exemplo do aproveitamento da capacidade j\u00e1 existente num centro de pesquisas, mostrando a import\u00e2ncia da proximidade f\u00edsica entre o grupo de pesquisa e o de engenharia b\u00e1sica, bem como da intera\u00e7\u00e3o entre ambos.\nFica evidente que, quando se desenvolve tecnologia, \u00e9 necess\u00e1rio que o grupo de pesquisa gere conhecimentos que ser\u00e3o utilizados pelo grupo de engenharia b\u00e1sica no projeto industrial.\nAl\u00e9m do mais, cabe ressaltar que, mesmo ap\u00f3s os estudos em escala de laborat\u00f3rio e piloto terem terminado, e o processo se encontrar em fase de-opera\u00e7\u00e3o da escala prot\u00f3tipo, \u00e9 importante a atua\u00e7\u00e3o do grupo de pesquisa, que continuar\u00e1 alimentando o desenvolvimento do pro\ncesso, esclarecendo d\u00favidas e gerando explica\u00e7\u00f5es sobre ocorr\u00eancias inesperadas que porventura tenham ocorrido.\n\u00c9 importante que se enfatize essa participa\u00e7\u00e3o da pesquisa no desenvolvimento de uma nova tecnologia, uma vez que, pelo fato de a cria\u00e7\u00e3o tecnol\u00f3gica ser incomum em pa\u00edses em desenvolvimento como o Brasil, seu processo n\u00e3o \u00e9 bem compreendido, mesmo por aqueles envolvidos diretamente em sua evolu\u00e7\u00e3o. No presente caso, apesar de todas as atividades desenvolvidas pela \u00e1rea de pesquisa, descritas sucintamente neste trabalho, muitos deixam de dar o devido cr\u00e9dito a essa participa\u00e7\u00e3o, por n\u00e3o entenderem que desenvolvimento tecnol\u00f3gico n\u00e3o \u00e9 simplesmente o projeto e opera\u00e7\u00e3o de uma unidade industrial.\nOutro aspecto importante ref\u00e9re-se ao descr\u00e9dito existente com rela\u00e7\u00e3o \u00e0s tecnologias desenvolvidas no Pa\u00eds. O exemplo de inova\u00e7\u00e3o tecnol\u00f3gica, aqui descrito, ilustra um caso em que o processo desenvolvido apresentou vantagens, sob todos os aspectos, quando confrontado com outras tecnologias importadas oferecidas. Mesmo assim, as dificuldades vividas para se enfrentarem as ofertas de tecnologias estrangeiras foram muito grandes. Isto serve de alerta para os problemas existentes quando surge a disputa entre tecnologia nacional e estrangeira, e a inova\u00e7\u00e3o nacional n\u00e3o apresenta condi\u00e7\u00f5es de suplantar a concorrente alien\u00edgena de maneira t\u00e3o ampla como no presente caso.\nFinalmente, outro ponto a ser considerado \u00e9 o da necessidade de se completar o pacote tecnol\u00f3gico, com a produ\u00e7\u00e3o no Pa\u00eds do catalisador desenvolvido no CENPES, o que possibilitar\u00e1 a total independ\u00eancia tecnol\u00f3gica do processo.\t.\nBIBLIOGRAFIA\nBARATELLI JR., F. Projeto eteno de \u00e1lcool. Petro &amp; Qu\u00edm., 4 (33), maio 1981.\nCHLAMTAC, E. B. Obten\u00e7\u00e3o de eteno a partir de etanol (l.\u00b0 relat\u00f3rio parcial). Rio de Janeiro, PETROBRAS. CENPES. DITER, 1976. (Relat\u00f3rio CENPES, 140).\nFARO JR., et alii. Obten\u00e7\u00e3o de eteno a partir de etanol (2.\u00b0 relat\u00f3rio parcial). Rio de Janeiro, PETROBR\u00c1S. CENPES. DITER, 1978. (Relat\u00f3rio CENPES, 169).\n__:_____Estudo da adsor\u00e7\u00e3o do sistema eteno-propeno sobre leitos de carv\u00e3o ativado. Rio de Janeiro, PETROBR\u00c1S. CENPES. DITER, 1979. (Relat\u00f3rio CENPES, 213).\nLEITAO, D. M. Contribui\u00e7\u00f5es do CENPES ao desenvolvimento tecnol\u00f3gico na \u00e1rea de processos qu\u00edmicos. Rev. Bras. Eng. Qu\u00edm., 6 (1/2): 60-8, abr./jun. 1982.\nPROJETO eteno de \u00e1lcool. Boi. T\u00e9c. Pet., 26(2): 160, abr./jun. 1983.\nVALLE, \u00c0. A. F. &amp; DIAS JR., J. F. Obten\u00e7\u00e3o de eteno a partir de etanol. Rio de Janeiro, PETROBR\u00c1S. CENPES. DITER, 1979.\nVILLA, R. Desenvolvimento de um novo processo para produ\u00e7\u00e3o de eteno a partir de etanol.In: CONGRESSO LATINO-AMERICANO DE PETROQU\u00cdMICA, 2, M\u00e9xico, 1978."}]}}}